{
  "buttons": [
    [
      "Предыдущая страница",
      "Текущая страница",
      "Следующая страница"
    ],
    [
      "\uD83C\uDFB2 Случайная техника"
    ],
    [
      "\uD83D\uDEAA В начало"
    ]
  ],
  "message": "Нажмите случайный выбор или введите номер техники",
  "message403": "Это эксклюзивная техника, и её нельзя смотреть без подписки. Пожалуйста купите подписку, если хотите прочитать эту техника.",
  "one_time_keyboard": false,
  "transitions": {
    "/start": "Start",
    "\uD83D\uDEAA В начало": "Start",
    "Предыдущая страница": "THIS",
    "Следующая страница": "THIS",
    "Текущая страница": "THIS",
    "\uD83C\uDFB2 Случайная техника": "THIS"
  }
}
